{
    "cardArray": [
      {
        "id": "3",
        "amountInDeck": 1,
        "title": "Showtime",
        "rule": "Show your boobs to %guyX or drink 5",
        "drink": false,
        "intercourse": true,
        "forBoysOrGirls": "girls",
        "expectsBoyOrGirl": "boy",
        "sexy": true
      },
      {
        "id": "4",
        "amountInDeck": 2,
        "title": "Moist Lips",
        "rule": "Drink 5 with %playerX or kiss %playerY",
        "drink": true,
        "intercourse": true,
        "forBoysOrGirls": "both",
        "expectsBoyOrGirl": "both",
        "sexy": true
      },
      {
        "id": "5",
        "amountInDeck": 2,
        "title": "Romeo",
        "rule": "Grab %girlX by her boobs or ass, and give us a rating 1-10",
        "drink": false,
        "intercourse": true,
        "forBoysOrGirls": "boys",
        "expectsBoyOrGirl": "girl",
        "sexy": true
      },
      {
        "id": "6",
        "amountInDeck": 1,
        "title": "Rock Paper Scissors",
        "rule": "Play with the player on your left, loser drinks 2",
        "drink": true,
        "intercourse": true,
        "forBoysOrGirls": "both",
        "expectsBoyOrGirl": "both",
        "sexy": false
      },
      {
        "id": "7",
        "amountInDeck": 1,
        "title": "Rock Paper Scissors",
        "rule": "Play with %playerX, loser drinks 4",
        "drink": true,
        "intercourse": true,
        "forBoysOrGirls": "both",
        "expectsBoyOrGirl": "both",
        "sexy": false
      },
      {
        "id": "8",
        "amountInDeck": 3,
        "title": "Give 2",
        "rule": "Pick a player to drink twice",
        "drink": true,
        "intercourse": false,
        "forBoysOrGirls": "both",
        "expectsBoyOrGirl": "both",
        "sexy": false
      },
      {
        "id": "9",
        "amountInDeck": 2,
        "title": "Bartender",
        "rule": "Pick a player to drink 3 times",
        "drink": true,
        "intercourse": false,
        "forBoysOrGirls": "both",
        "expectsBoyOrGirl": "both",
        "sexy": false
      },
      {
        "id": "10",
        "amountInDeck": 2,
        "title": "Barkeeper",
        "rule": "Pick a player to drink 4 times",
        "drink": true,
        "intercourse": false,
        "forBoysOrGirls": "both",
        "expectsBoyOrGirl": "both",
        "sexy": false
      },
      {
        "id": "11",
        "amountInDeck": 1,
        "title": "Four eyes",
        "rule": "Every player wearing glasses drinks",
        "drink": true,
        "intercourse": false,
        "forBoysOrGirls": "both",
        "expectsBoyOrGirl": "both",
        "sexy": false
      },
      {
        "id": "12",
        "amountInDeck": 1,
        "title": "Share the love",
        "rule": "Pick 3 players to drink 3 times",
        "drink": true,
        "intercourse": false,
        "forBoysOrGirls": "both",
        "expectsBoyOrGirl": "both",
        "sexy": false
      },
      {
        "id": "13",
        "amountInDeck": 2,
        "title": "Casual Alcoholic", 
        "rule": "Drink 3 Times",
        "drink": true,
        "intercourse": false,
        "forBoysOrGirls": "both",
        "expectsBoyOrGirl": "both",
        "sexy": false
      },
      {
        "id": "14",
        "amountInDeck": 2,
        "title": "Raging Alcoholic",
        "rule": "Drink 5 Times",
        "drink": true,
        "intercourse": false,
        "forBoysOrGirls": "both",
        "expectsBoyOrGirl": "both",
        "sexy": false
      },
      {
        "id": "15",
        "amountInDeck": 2,
        "title": "Social",
        "rule": "Everyone drinks",
        "drink": true,
        "intercourse": false,
        "forBoysOrGirls": "both",
        "expectsBoyOrGirl": "both",
        "sexy": false
      },
      {
        "id": "16",
        "amountInDeck": 2,
        "title": "Down The Hatch",
        "rule": "Finish your drink",
        "drink": true,
        "intercourse": false,
        "forBoysOrGirls": "both",
        "expectsBoyOrGirl": "both",
        "sexy": false
      },
      {
        "id": "17",
        "amountInDeck": 2,
        "title": "Peer Pressure",
        "rule": "Drink once for each player",
        "drink": true,
        "intercourse": false,
        "forBoysOrGirls": "both",
        "expectsBoyOrGirl": "both",
        "sexy": false
      },
      {
        "id": "18",
        "amountInDeck": 1,
        "title": "Flip a cup!",
        "rule": "Flip a cup and drink once for every failed attempt. If there is no cup, drink 5",
        "drink": true,
        "intercourse": false,
        "forBoysOrGirls": "both",
        "expectsBoyOrGirl": "both",
        "sexy": false
      },
      {
        "id": "19",
        "amountInDeck": 1,
        "title": "Lurch",
        "rule": "Tallest player ingame drinks",
        "drink": true,
        "intercourse": false,
        "forBoysOrGirls": "both",
        "expectsBoyOrGirl": "both",
        "sexy": false
      },
      {
        "id": "20",
        "amountInDeck": 1,
        "title": "Smurf",
        "rule": "Shortest player ingame drinks",
        "drink": true,
        "intercourse": false,
        "forBoysOrGirls": "both",
        "expectsBoyOrGirl": "both",
        "sexy": false
      },
      {
        "id": "21",
        "amountInDeck": 1,
        "title": "Bipolar",
        "rule": "Insult the player on your right and compliment left",
        "drink": true,
        "intercourse": false,
        "forBoysOrGirls": "both",
        "expectsBoyOrGirl": "both",
        "sexy": false
      },
      {
        "id": "22",
        "amountInDeck": 1,
        "title": "Rainbow Warrior",
        "rule": "Pick a color, everyone wearing that color drinks",
        "drink": true,
        "intercourse": false,
        "forBoysOrGirls": "both",
        "expectsBoyOrGirl": "both",
        "sexy": false
      },
      {
        "id": "23",
        "amountInDeck": 2,
        "title": "Stud",
        "rule": "Everyone who finds you attractive drinks",
        "drink": true,
        "intercourse": false,
        "forBoysOrGirls": "both",
        "expectsBoyOrGirl": "both",
        "sexy": false
      },
      {
        "id": "24",
        "amountInDeck": 1,
        "title": "Crush",
        "rule": "The player who you find the most attractive drinks 4",
        "drink": true,
        "intercourse": false,
        "forBoysOrGirls": "both",
        "expectsBoyOrGirl": "both",
        "sexy": false
      },
      {
        "id": "25",
        "amountInDeck": 1,
        "title": "Bling Bling",
        "rule": "Drinks for every accessory you are wearing",
        "drink": true,
        "intercourse": false,
        "forBoysOrGirls": "both",
        "expectsBoyOrGirl": "both",
        "sexy": false
      },
      {
        "id": "X",
        "amountInDeck": 3,
        "title": "Rule",
        "rule": "Make up a rule that everyone must follow until another rule card is drawn. Everytime someone breaks the rule, they must drink",
        "drink": true,
        "intercourse": false,
        "forBoysOrGirls": "both",
        "expectsBoyOrGirl": "both",
        "sexy": false
      },
      {
        "id": "X",
        "amountInDeck": 1,
        "title": "Cat Lady",
        "rule": "All Cat Owners drink once",
        "drink": true,
        "intercourse": false,
        "forBoysOrGirls": "both",
        "expectsBoyOrGirl": "both",
        "sexy": false
      },
      {
        "id": "X",
        "amountInDeck": 1,
        "title": "Crypt Keeper",
        "rule": "Oldest player drinks",
        "drink": true,
        "intercourse": false,
        "forBoysOrGirls": "both",
        "expectsBoyOrGirl": "both",
        "sexy": false
      },
      {
        "id": "X",
        "amountInDeck": 1,
        "title": "Embryo",
        "rule": "Youngest player drinks",
        "drink": true,
        "intercourse": false,
        "forBoysOrGirls": "both",
        "expectsBoyOrGirl": "both",
        "sexy": false
      },
      {
        "id": "X",
        "amountInDeck": 1,
        "title": "Never have i ever",
        "rule": "Play a game of never have i ever. Who has done it, drinks 2",
        "drink": true,
        "intercourse": false,
        "forBoysOrGirls": "both",
        "expectsBoyOrGirl": "both",
        "sexy": false
      },
      {
        "id": "X",
        "amountInDeck": 1,
        "title": "Wild Card",
        "rule": "The player you find the craziest drinks",
        "drink": true,
        "intercourse": false,
        "forBoysOrGirls": "both",
        "expectsBoyOrGirl": "both",
        "sexy": false
      },
      {
        "id": "X",
        "amountInDeck": 1,
        "title": "Nice Ink",
        "rule": "Everyone with a Tattoo drinks for as many tattoos as they have",
        "drink": true,
        "intercourse": false,
        "forBoysOrGirls": "both",
        "expectsBoyOrGirl": "both",
        "sexy": false
      },
      {
        "id": "X",
        "amountInDeck": 1,
        "title": "Chicks",
        "rule": "All Girls drink, and %girlX drinks double",
        "drink": true,
        "intercourse": false,
        "forBoysOrGirls": "both",
        "expectsBoyOrGirl": "girl",
        "sexy": false
      },
      {
        "id": "X",
        "amountInDeck": 1,
        "title": "Dicks",
        "rule": "All guys drink, and %boyX drinks double",
        "drink": true,
        "intercourse": false,
        "forBoysOrGirls": "both",
        "expectsBoyOrGirl": "boy",
        "sexy": false
      },
      {
        "id": "X",
        "amountInDeck": 1,
        "title": "Liar Liar",
        "rule": "Tell everyone",
        "drink": false,
        "intercourse": false,
        "forBoysOrGirls": "both",
        "expectsBoyOrGirl": "both",
        "sexy": false
      },
      {
        "id": "X",
        "amountInDeck": 1,
        "title": "Mute",
        "rule": "Cant talk until your next turn",
        "drink": true,
        "intercourse": false,
        "forBoysOrGirls": "both",
        "expectsBoyOrGirl": "both",
        "sexy": false
      },
      {
        "id": "X",
        "amountInDeck": 1,
        "title": "Sharing is Caring",
        "rule": "Drink together with your friend %playerX",
        "drink": true,
        "intercourse": false,
        "forBoysOrGirls": "both",
        "expectsBoyOrGirl": "both",
        "sexy": false
      },
      {
        "id": "X",
        "amountInDeck": 1,
        "title": "Lovers",
        "rule": "Pick someone to drink with you for the rest of the game",
        "drink": true,
        "intercourse": false,
        "forBoysOrGirls": "both",
        "expectsBoyOrGirl": "both",
        "sexy": false
      },
      {
        "id": "X",
        "amountInDeck": 1,
        "title": "Hi five!",
        "rule": "Choose a player to drink 5 times with",
        "drink": true,
        "intercourse": false,
        "forBoysOrGirls": "both",
        "expectsBoyOrGirl": "both",
        "sexy": false
      },
      {
        "id": "X",
        "amountInDeck": 1,
        "title": "Casanova",
        "rule": "Kiss the player on your right",
        "drink": true,
        "intercourse": true,
        "forBoysOrGirls": "both",
        "expectsBoyOrGirl": "both",
        "sexy": true
      },
      {
        "id": "X",
        "amountInDeck": 2,
        "title": "Strip",
        "rule": "Remove a piece of clothing for the rest of the game",
        "drink": true,
        "intercourse": false,
        "forBoysOrGirls": "both",
        "expectsBoyOrGirl": "both",
        "sexy": false
      },
      {
        "id": "X",
        "amountInDeck": 1,
        "title": "Hands Across",
        "rule": "Keep physical contact with the player on your left until your next turn",
        "drink": true,
        "intercourse": true,
        "forBoysOrGirls": "both",
        "expectsBoyOrGirl": "both",
        "sexy": false
      },
      {
        "id": "X",
        "amountInDeck": 1,
        "title": "Bipolar",
        "rule": "Slap the player on the left and kiss the player after",
        "drink": true,
        "intercourse": true,
        "forBoysOrGirls": "both",
        "expectsBoyOrGirl": "both",
        "sexy": true
      },
      {
        "id": "X",
        "amountInDeck": 1,
        "title": "Fresh meat",
        "rule": "Player who most recently had sex drinks 3 times",
        "drink": true,
        "intercourse": false,
        "forBoysOrGirls": "both",
        "expectsBoyOrGirl": "both",
        "sexy": true
      },
      {
        "id": "X",
        "amountInDeck": 1,
        "title": "Dracula",
        "rule": "Bite a player of your choice in the neck",
        "drink": false,
        "intercourse": true,
        "forBoysOrGirls": "both",
        "expectsBoyOrGirl": "both",
        "sexy": true
      },
      {
        "id": "X",
        "amountInDeck": 1,
        "title": "50 Shades of Gray",
        "rule": "Every player who has been spanked (in bed) drinks",
        "drink": true,
        "intercourse": false,
        "forBoysOrGirls": "both",
        "expectsBoyOrGirl": "both",
        "sexy": true
      },
      {
        "id": "X",
        "amountInDeck": 1,
        "title": "Harderbaby",
        "rule": "Pick a player to spank you",
        "drink": true,
        "intercourse": true,
        "forBoysOrGirls": "both",
        "expectsBoyOrGirl": "both",
        "sexy": true
      },
      {
        "id": "X",
        "amountInDeck": 1,
        "title": "Bi curious",
        "rule": "Everyone who has kissed their same gender drinks 3 times",
        "drink": true,
        "intercourse": false,
        "forBoysOrGirls": "both",
        "expectsBoyOrGirl": "both",
        "sexy": true
      },
      {
        "id": "X",
        "amountInDeck": 2,
        "title": "Spank Machine",
        "rule": "Get spanked by every player",
        "drink": true,
        "intercourse": false,
        "forBoysOrGirls": "girls",
        "expectsBoyOrGirl": "both",
        "sexy": true
      },
      {
        "id": "X",
        "amountInDeck": 1,
        "title": "Ripped",
        "rule": "Do 10 push ups or drink 5",
        "drink": true,
        "intercourse": false,
        "forBoysOrGirls": "both",
        "expectsBoyOrGirl": "both",
        "sexy": false
      },
      {
        "id": "X",
        "amountInDeck": 3,
        "title": "New Question Master",
        "rule": "If a player replies to a question they drink once",
        "drink": true,
        "intercourse": false,
        "forBoysOrGirls": "both",
        "expectsBoyOrGirl": "both",
        "sexy": false
      },
      {
        "id": "X",
        "amountInDeck": 1,
        "title": "Curious",
        "rule": "Have you ever seen %playerX naked? If yes, drink 3",
        "drink": true,
        "intercourse": false,
        "forBoysOrGirls": "both",
        "expectsBoyOrGirl": "both",
        "sexy": true
      },
      {
        "id": "X",
        "amountInDeck": 2,
        "title": "Lapdance",
        "rule": "Sit on %guyX's lap until your next turn",
        "drink": false,
        "intercourse": true,
        "forBoysOrGirls": "girls",
        "expectsBoyOrGirl": "boy",
        "sexy": true
      },
      {
        "id": "X",
        "amountInDeck": 2,
        "title": "Drunk",
        "rule": "Did you drink more then %playerX? If not, drink 4",
        "drink": true,
        "intercourse": false,
        "forBoysOrGirls": "both",
        "expectsBoyOrGirl": "both",
        "sexy": false
      },
      {
        "id": "X",
        "amountInDeck": 1,
        "title": "Too sober?",
        "rule": "Who is the most sober player? Choose who has to drink 5",
        "drink": true,
        "intercourse": false,
        "forBoysOrGirls": "both",
        "expectsBoyOrGirl": "both",
        "sexy": false
      },
      {
        "id": "X",
        "amountInDeck": 1,
        "title": "Acrobat",
        "rule": "Take a drink without using your hands, or finish your drink",
        "drink": true,
        "intercourse": false,
        "forBoysOrGirls": "both",
        "expectsBoyOrGirl": "both",
        "sexy": false
      },
      {
        "id": "X",
        "amountInDeck": 1,
        "title": "Motorboat",
        "rule": "Motorboat the person to your right for 5 seconds, even if they don't have boobs. Or drink 5",
        "drink": true,
        "intercourse": true,
        "forBoysOrGirls": "both",
        "expectsBoyOrGirl": "both",
        "sexy": true
      },
      {
        "id": "X",
        "amountInDeck": 1,
        "title": "Poor",
        "rule": "Drink 3 if you have a cracked phone screen",
        "drink": true,
        "intercourse": false,
        "forBoysOrGirls": "both",
        "expectsBoyOrGirl": "both",
        "sexy": false
      },
      {
        "id": "X",
        "amountInDeck": 1,
        "title": "Blondes",
        "rule": "All blondes must drink",
        "drink": true,
        "intercourse": false,
        "forBoysOrGirls": "both",
        "expectsBoyOrGirl": "both",
        "sexy": false
      },
      {
        "id": "X",
        "amountInDeck": 1,
        "title": "Brunettes",
        "rule": "All brunettes must drink",
        "drink": true,
        "intercourse": false,
        "forBoysOrGirls": "both",
        "expectsBoyOrGirl": "both",
        "sexy": false
      },
      {
        "id": "X",
        "amountInDeck": 1,
        "title": "Simon",
        "rule": "Everyone plays 'Simon Says' and you are Simon. The first player that messes up must drink",
        "drink": true,
        "intercourse": true,
        "forBoysOrGirls": "both",
        "expectsBoyOrGirl": "both",
        "sexy": false
      },
      {
        "id": "X",
        "amountInDeck": 4,
        "title": "Undress",
        "rule": "Take one piece of cloth off",
        "drink": false,
        "intercourse": false,
        "forBoysOrGirls": "girls",
        "expectsBoyOrGirl": "both",
        "sexy": true
      }
    ]
  }